[
  {
    "IlceAdi": "BAHAWALPUR",
    "IlceAdiEn": "BAHAWALPUR",
    "IlceID": "15789"
  },
  {
    "IlceAdi": "CHINIOT",
    "IlceAdiEn": "CHINIOT",
    "IlceID": "15773"
  },
  {
    "IlceAdi": "DERA GHAZI KHAN",
    "IlceAdiEn": "DERA GHAZI KHAN",
    "IlceID": "15790"
  },
  {
    "IlceAdi": "FAISALABAD",
    "IlceAdiEn": "FAISALABAD",
    "IlceID": "15770"
  },
  {
    "IlceAdi": "GUJRANWALA",
    "IlceAdiEn": "GUJRANWALA",
    "IlceID": "15774"
  },
  {
    "IlceAdi": "GUJRAT",
    "IlceAdiEn": "GUJRAT",
    "IlceID": "15772"
  },
  {
    "IlceAdi": "HYDERABAD",
    "IlceAdiEn": "HYDERABAD",
    "IlceID": "15775"
  },
  {
    "IlceAdi": "ISLAMABAD",
    "IlceAdiEn": "ISLAMABAD",
    "IlceID": "15766"
  },
  {
    "IlceAdi": "JHANG SADAR",
    "IlceAdiEn": "JHANG SADAR",
    "IlceID": "15788"
  },
  {
    "IlceAdi": "KARACHI",
    "IlceAdiEn": "KARACHI",
    "IlceID": "15767"
  },
  {
    "IlceAdi": "KASUR",
    "IlceAdiEn": "KASUR",
    "IlceID": "15771"
  },
  {
    "IlceAdi": "LAHOR",
    "IlceAdiEn": "LAHOR",
    "IlceID": "15793"
  },
  {
    "IlceAdi": "LARKANA",
    "IlceAdiEn": "LARKANA",
    "IlceID": "15777"
  },
  {
    "IlceAdi": "MARDAN",
    "IlceAdiEn": "MARDAN",
    "IlceID": "15778"
  },
  {
    "IlceAdi": "MIRPUR KHAS",
    "IlceAdiEn": "MIRPUR KHAS",
    "IlceID": "15779"
  },
  {
    "IlceAdi": "MULTAN",
    "IlceAdiEn": "MULTAN",
    "IlceID": "15769"
  },
  {
    "IlceAdi": "NAWABSHAH",
    "IlceAdiEn": "NAWABSHAH",
    "IlceID": "15791"
  },
  {
    "IlceAdi": "OKARA",
    "IlceAdiEn": "OKARA",
    "IlceID": "15786"
  },
  {
    "IlceAdi": "PESHAWER",
    "IlceAdiEn": "PESHAWER",
    "IlceID": "15768"
  },
  {
    "IlceAdi": "QUETTA",
    "IlceAdiEn": "QUETTA",
    "IlceID": "15780"
  },
  {
    "IlceAdi": "RAHIMYAR KHAN",
    "IlceAdiEn": "RAHIMYAR KHAN",
    "IlceID": "15781"
  },
  {
    "IlceAdi": "RAWALPINDI",
    "IlceAdiEn": "RAWALPINDI",
    "IlceID": "15782"
  },
  {
    "IlceAdi": "SAHIWAL",
    "IlceAdiEn": "SAHIWAL",
    "IlceID": "15787"
  },
  {
    "IlceAdi": "SARGODHA",
    "IlceAdiEn": "SARGODHA",
    "IlceID": "15783"
  },
  {
    "IlceAdi": "SHEKHUPURA",
    "IlceAdiEn": "SHEKHUPURA",
    "IlceID": "15784"
  },
  {
    "IlceAdi": "SIALKOT",
    "IlceAdiEn": "SIALKOT",
    "IlceID": "15785"
  },
  {
    "IlceAdi": "SUKHUR",
    "IlceAdiEn": "SUKHUR",
    "IlceID": "15792"
  },
  {
    "IlceAdi": "WAH",
    "IlceAdiEn": "WAH",
    "IlceID": "15776"
  }
]